streamlit_terran_timeline/__init__.py
streamlit_terran_timeline/dashboard.py
streamlit_terran_timeline/example.py
streamlit_terran_timeline/frontend/build/asset-manifest.json
streamlit_terran_timeline/frontend/build/bootstrap.min.css
streamlit_terran_timeline/frontend/build/index.html
streamlit_terran_timeline/frontend/build/precache-manifest.267519fb05bfd8914da80d958c90c140.js
streamlit_terran_timeline/frontend/build/precache-manifest.531114a980e33ffa6e6ade92abb4188b.js
streamlit_terran_timeline/frontend/build/precache-manifest.5b3b535687c69cdd5bc6464300c6a8ff.js
streamlit_terran_timeline/frontend/build/precache-manifest.7f2314780a7d9b112508c0043091527a.js
streamlit_terran_timeline/frontend/build/precache-manifest.c603b68ce3ef222ead18750d653e97d9.js
streamlit_terran_timeline/frontend/build/precache-manifest.f14ca7cef67822a176a5d179036c72df.js
streamlit_terran_timeline/frontend/build/service-worker.js
streamlit_terran_timeline/frontend/build/terran-square.svg
streamlit_terran_timeline/frontend/build/static/css/2.11829350.chunk.css
streamlit_terran_timeline/frontend/build/static/css/2.11829350.chunk.css.map
streamlit_terran_timeline/frontend/build/static/css/2.ed439b8d.chunk.css
streamlit_terran_timeline/frontend/build/static/css/2.ed439b8d.chunk.css.map
streamlit_terran_timeline/frontend/build/static/css/main.2d44f724.chunk.css
streamlit_terran_timeline/frontend/build/static/css/main.2d44f724.chunk.css.map
streamlit_terran_timeline/frontend/build/static/css/main.fbdcb4e7.chunk.css
streamlit_terran_timeline/frontend/build/static/css/main.fbdcb4e7.chunk.css.map
streamlit_terran_timeline/frontend/build/static/js/2.14c28671.chunk.js
streamlit_terran_timeline/frontend/build/static/js/2.14c28671.chunk.js.LICENSE.txt
streamlit_terran_timeline/frontend/build/static/js/2.14c28671.chunk.js.map
streamlit_terran_timeline/frontend/build/static/js/2.c86bf2e7.chunk.js
streamlit_terran_timeline/frontend/build/static/js/2.c86bf2e7.chunk.js.LICENSE.txt
streamlit_terran_timeline-0.0.19.dist-info/LICENSE
streamlit_terran_timeline-0.0.19.dist-info/METADATA
streamlit_terran_timeline-0.0.19.dist-info/WHEEL
streamlit_terran_timeline-0.0.19.dist-info/top_level.txt
streamlit_terran_timeline-0.0.19.dist-info/RECORD
