Metadata-Version: 2.1
Name: streamlit-terran-timeline
Version: 0.0.19
Summary: Create faces timelines from videos
Home-page: https://github.com/pento-group/streamlit-terran-timeline
Author: Pento AI
Author-email: hello@pento.ai
License: UNKNOWN
Platform: UNKNOWN
Requires-Python: >=3.6
Requires-Dist: streamlit (>=0.63)
